Metadata-Version: 1.0
Name: SDCOM
Version: 1.0.0b1
Summary: An attempt to recreate the module to work with the server-discord.com API
Home-page: https://discord.gg/8Cey77R
Author: NickSaltFoxu
Author-email: senyaprojectg@gmail.com
License: MPL-2.0
Platform: UNKNOWN
